{"author":"ejgallego","number":107,"diff_summary":[{"file":".travis.yml","status":"M","additions":11,"deletions":9}],"state":"merged","open_date":"2017-02-07T12:54:58Z","update_date":"2017-02-21T09:07:57Z","discussion":[],"review_discussion":[],"tags":[],"commits":[{"author":"ejgallego","committer":"ejgallego","hash":"62b3f78ee8cb16fcaa95ba7051d050c0e2913018","message":"[travis] Make v8.5 build again\n\nWe also remove PFsection6 from build as it seems to be too close.","date":"2017-02-07T12:42:35Z"}]}