{"author":"ppedrot","number":40,"diff_summary":[{"file":"mathcomp/ssreflect/plugin/trunk/ssreflect.ml4","status":"M","additions":2,"deletions":12}],"state":"merged","open_date":"2016-05-02T09:39:59Z","update_date":"2016-05-04T12:15:00Z","discussion":[{"author":"gares","date":"2016-05-04T12:15:05Z","comment":"Thanks\n"}],"review_discussion":[],"tags":[],"commits":[{"author":"ppedrot","committer":"ppedrot","hash":"35d6aa4bc7c2d39bbd55d2ff5d114a03e1f284f2","message":"Fixing compilation after the merge of ML-tactic-notation branch.","date":"2016-05-02T09:34:40Z"}]}