{"author":"CohenCyril","number":725,"diff_summary":[{"file":".github/workflows/nix-action.yml","status":"M","additions":12,"deletions":12},{"file":".nix/config.nix","status":"M","additions":12,"deletions":12},{"file":".nix/coq-nix-toolbox.nix","status":"M","additions":12,"deletions":12},{"file":"default.nix","status":"M","additions":12,"deletions":12}],"state":"merged","open_date":"2021-03-17T02:42:02Z","update_date":"2021-03-17T17:54:38Z","discussion":[],"review_discussion":[],"tags":[{"tag":"kind: CI","description":"Issue or PR about the CI. (Gitlab CI or CI of dependencies problems linked with math-comp)"}],"commits":[{"author":"CohenCyril","committer":"CohenCyril","hash":"bbec40b5aed2cd70c95ad7b11bf264b6d283885e","message":"up","date":"2021-03-17T17:25:57Z"}]}