{"author":"affeldt-aist","number":797,"diff_summary":[{"file":"CHANGELOG_UNRELEASED.md","status":"M","additions":1,"deletions":1}],"state":"merged","open_date":"2021-10-09T01:41:37Z","update_date":"2021-10-10T10:32:12Z","discussion":[],"review_discussion":[],"tags":[{"tag":"kind: documentation","description":"Issue or PR about documentation mistakes, deficiencies, enhancements, ..."}],"commits":[{"author":"affeldt-aist","committer":"affeldt-aist","hash":"8f03f021d6d4b056acb15b5920f85c56f0275cb2","message":"typo","date":"2021-10-09T01:40:56Z"}]}